README.rst
setup.py
footballdataorg/__init__.py
footballdataorg/exceptions.py
footballdataorg/fd.py
footballdataorg/request_handler.py
footballdataorg/service.py
footballdataorg.egg-info/PKG-INFO
footballdataorg.egg-info/SOURCES.txt
footballdataorg.egg-info/dependency_links.txt
footballdataorg.egg-info/requires.txt
footballdataorg.egg-info/top_level.txt
tests/__init__.py
tests/context.py
tests/test_sample.py