Metadata-Version: 1.1
Name: footballdataorg
Version: 0.1.6
Summary: A wrapper for the football-data.org api
Home-page: https://github.com/hhllcks/footballdataorg
Author: Hendrik Hilleckes
Author-email: hhllcks@gmail.com
License: UNKNOWN
Platform: UNKNOWN
Classifier: Development Status :: 3 - Alpha
Classifier: Programming Language :: Python
Classifier: Programming Language :: Python :: 3 :: Only
Classifier: Programming Language :: Python :: 3.6
